PyOghma/Calculate.py
PyOghma/Epitaxy.py
PyOghma/Fitting.py
PyOghma/ML.py
PyOghma/OghmaNano.py
PyOghma/OghmaResults.py
PyOghma/Optical.py
PyOghma/Server.py
PyOghma/Sims.py
PyOghma/Thermal.py
PyOghma/__init__.py
PyOghma/Sim_Defaults/__init__.py
PyOghma/Sim_Defaults/Epitaxy/shape_dos/default.json
PyOghma/Sim_Defaults/Fits/duplicate/default.json
PyOghma/Sim_Defaults/Fits/fit_config/default.json
PyOghma/Sim_Defaults/Fits/fits/config/default.json
PyOghma/Sim_Defaults/Fits/fits/fit_patch/default.json
PyOghma/Sim_Defaults/Fits/fits/import_config/default.json
PyOghma/Sim_Defaults/Fits/rules/default.json
PyOghma/Sim_Defaults/Fits/vars/default.json
PyOghma/Sim_Defaults/Ml/ml_config/default.json
PyOghma/Sim_Defaults/Ml/ml_networks/config/default.json
PyOghma/Sim_Defaults/Ml/ml_networks/segment/default.json
PyOghma/Sim_Defaults/Ml/ml_networks/segment/ml_network_inputs/default.json
PyOghma/Sim_Defaults/Ml/ml_networks/segment/ml_network_outputs/default.json
PyOghma/Sim_Defaults/Ml/ml_random/default.json
PyOghma/Sim_Defaults/Ml/ml_sims/ml_output_vectors/default.json
PyOghma/Sim_Defaults/Ml/ml_sims/ml_output_vectors/import_config/default.json
PyOghma/Sim_Defaults/Ml/ml_sims/ml_patch/default.json
PyOghma/Sim_Defaults/Optical/configs/lasers/default.json
PyOghma/Sim_Defaults/Optical/configs/light/default.json
PyOghma/Sim_Defaults/Optical/configs/light_sources/default.json
PyOghma/Sim_Defaults/Optical/configs/spectral2/default.json
PyOghma/Sim_Defaults/Sim/configs/default.json
PyOghma/Sim_Defaults/Sims/configs/ce/default.json
PyOghma/Sim_Defaults/Sims/configs/cv/default.json
PyOghma/Sim_Defaults/Sims/configs/eqe/default.json
PyOghma/Sim_Defaults/Sims/configs/fx_domain/segment.json
PyOghma/Sim_Defaults/Sims/configs/fx_domain/IS/default.json
PyOghma/Sim_Defaults/Sims/configs/fx_domain/imps/default.json
PyOghma/Sim_Defaults/Sims/configs/fx_domain/imvs/default.json
PyOghma/Sim_Defaults/Sims/configs/jv/default.json
PyOghma/Sim_Defaults/Sims/configs/pl/default.json
pyoghma-0.0.55.dist-info/METADATA
pyoghma-0.0.55.dist-info/WHEEL
pyoghma-0.0.55.dist-info/licenses/LICENSE
pyoghma-0.0.55.dist-info/RECORD
