Metadata-Version: 2.4
Name: PyOghma
Version: 0.0.55
Summary: A Python API for OghmaNano
Project-URL: Homepage, https://github.com/CaiWilliams/pyOghma
Project-URL: Issues, https://github.com/CaiWilliams/pyOghma/issues
Author-email: Cai Williams <cai.williams@physik.tu-chemnitz.de>
License-File: LICENSE
Requires-Dist: mgzip>=0.2.1
Requires-Dist: numpy>=1.26.4
Requires-Dist: pandas>=2.2.2
Requires-Dist: scipy>=1.15.2
Requires-Dist: tqdm>=4.66.2
Requires-Dist: ujson>=5.9.0
